orm_sqlite/__init__.py
orm_sqlite/database.py
orm_sqlite/logger.py
orm_sqlite/manager.py
orm_sqlite/model.py
ORM_SQLite-0.0.2.dist-info/LICENSE
ORM_SQLite-0.0.2.dist-info/METADATA
ORM_SQLite-0.0.2.dist-info/WHEEL
ORM_SQLite-0.0.2.dist-info/top_level.txt
ORM_SQLite-0.0.2.dist-info/RECORD
