Metadata-Version: 2.1
Name: ORM-SQLite
Version: 0.0.2
Summary: A lightweight ORM for SQLite
Home-page: https://github.com/yzhang-dev/ORM-SQLite
Author: Yi Zhang
Author-email: yizhang.dev@gmail.com
License: MIT
Download-URL: https://github.com/yzhang-dev/ORM-SQLite
Keywords: orm,sqlite3
Platform: UNKNOWN
Classifier: License :: OSI Approved :: MIT License
Classifier: Operating System :: OS Independent
Classifier: Programming Language :: Python :: 3
Classifier: Programming Language :: Python :: 3.7
Requires-Python: >=3.7
